awskit/__init__.py
awskit/config.py
awskit/converter.py
awskit/exceptions.py
awskit/logging_config.py
awskit/metrics.py
awskit/py.typed
awskit/sqs/__init__.py
awskit/sqs/acknowledgement.py
awskit/sqs/backpressure.py
awskit/sqs/container.py
awskit/sqs/context.py
awskit/sqs/decorator.py
awskit/sqs/models.py
awskit/sqs/registry.py
awskit/sqs/template.py
awskit-1.0.1.dist-info/licenses/LICENSE
awskit-1.0.1.dist-info/METADATA
awskit-1.0.1.dist-info/WHEEL
awskit-1.0.1.dist-info/top_level.txt
awskit-1.0.1.dist-info/RECORD
