Metadata-Version: 2.4
Name: awskit
Version: 1.0.1
Summary: A Pythonic, Spring-inspired toolkit for AWS services with decorator-based patterns, automatic message conversion, and flexible configuration strategies
Author: YelkuriRaghavendra
Maintainer: YelkuriRaghavendra
License: MIT
Keywords: aws,sqs,sns,dynamodb,messaging,queue,boto3,spring,decorator,toolkit
Classifier: Development Status :: 3 - Alpha
Classifier: Intended Audience :: Developers
Classifier: License :: OSI Approved :: MIT License
Classifier: Operating System :: OS Independent
Classifier: Programming Language :: Python :: 3
Classifier: Programming Language :: Python :: 3.9
Classifier: Programming Language :: Python :: 3.10
Classifier: Programming Language :: Python :: 3.11
Classifier: Programming Language :: Python :: 3.12
Classifier: Programming Language :: Python :: 3 :: Only
Classifier: Topic :: Software Development :: Libraries :: Python Modules
Classifier: Topic :: System :: Distributed Computing
Classifier: Typing :: Typed
Requires-Python: >=3.9
License-File: LICENSE
Requires-Dist: boto3<2.0.0,>=1.26.0
Requires-Dist: typing-extensions<5.0.0,>=4.5.0
Requires-Dist: structlog<25.0.0,>=23.1.0
Provides-Extra: metrics
Requires-Dist: prometheus-client<1.0.0,>=0.16.0; extra == "metrics"
Requires-Dist: statsd<5.0.0,>=3.3.0; extra == "metrics"
Provides-Extra: dev
Requires-Dist: pytest<9.0.0,>=7.0.0; extra == "dev"
Requires-Dist: pytest-cov<5.0.0,>=4.0.0; extra == "dev"
Requires-Dist: hypothesis<7.0.0,>=6.0.0; extra == "dev"
Requires-Dist: black<25.0.0,>=23.0.0; extra == "dev"
Dynamic: license-file
